pyside_demo/__init__.py
pyside_demo/__main__.py
pyside_demo/db/__init__.py
pyside_demo/db/database.py
pyside_demo/db/sql.py
pyside_demo/gui/__init__.py
pyside_demo/gui/data.py
pyside_demo/gui/dialog.py
pyside_demo/gui/graph.py
pyside_demo/gui/home.py
pyside_demo/gui/map.py
pyside_demo/gui/settings.py
pyside_demo/gui/sidebar.py
pyside_demo/gui/table.py
pyside_demo/gui/top_menu.py
pyside_demo/gui/window.py
pyside_demo/model/__init__.py
pyside_demo/model/table.py
pyside_demo/resources/__init__.py
pyside_demo/resources/icons/deltodon-logo.png
pyside_demo/resources/rc_resources.py
pyside_demo/resources/ui_mainwindow.py
pyside_demo/theme/__init__.py
pyside_demo/theme/dark.qss
pyside_demo/theme/theme.py
pyside_demo-0.2.1.dist-info/LICENSE
pyside_demo-0.2.1.dist-info/METADATA
pyside_demo-0.2.1.dist-info/WHEEL
pyside_demo-0.2.1.dist-info/RECORD
