Metadata-Version: 2.1
Name: pyside-demo
Version: 0.2.1
Summary: Offline-first GUI application with PostgreSQL synchronization
Home-page: https://github.com/jiriklic/pyside-demo
License: MIT
Keywords: PySide6,Offline-first,GUI
Author: Jiri Klic
Author-email: web@jiriklic.com
Requires-Python: >=3.9,<3.13
Classifier: Development Status :: 1 - Planning
Classifier: Intended Audience :: Developers
Classifier: Intended Audience :: Science/Research
Classifier: License :: OSI Approved :: MIT License
Classifier: Natural Language :: English
Classifier: Programming Language :: Python :: 3
Classifier: Programming Language :: Python :: 3.9
Classifier: Programming Language :: Python :: 3.10
Classifier: Programming Language :: Python :: 3.11
Classifier: Programming Language :: Python :: 3.12
Classifier: Programming Language :: Python :: Implementation :: CPython
Classifier: Topic :: Scientific/Engineering :: Atmospheric Science
Classifier: Topic :: Scientific/Engineering :: GIS
Classifier: Topic :: Software Development :: Libraries :: Python Modules
Requires-Dist: folium (>=0.17.0,<0.18.0)
Requires-Dist: pandas (>=2.2.3,<3.0.0)
Requires-Dist: psycopg2-binary (>=2.9.9,<3.0.0)
Requires-Dist: pyqtgraph (>=0.13.7,<0.14.0)
Requires-Dist: pyside6 (>=6.7.2,<7.0.0)
Requires-Dist: python-dotenv (>=1.0.1,<2.0.0)
Requires-Dist: qtawesome (>=1.3.1,<2.0.0)
Requires-Dist: requests (>=2.31.0,<3.0.0)
Requires-Dist: sqlalchemy (>=2.0.23,<3.0.0)
Project-URL: Repository, https://github.com/jiriklic/pyside-demo
